{
    "name": "mayhem",
    "script": [
        {
            "item_pool": ["Broom", "Candle", "Skull"],
            "success_count": 3,
            "item_delay": 5,
            "item_timeout": 14,
            "item_spawn_delay": 0.25
        },
        {
            "item_pool": ["Hat", "Candle", "Skull"],
            "success_count": 1,
            "item_delay": 3,
            "item_timeout": 12,
            "item_spawn_delay": 0.25
        },
        {
            "item_pool": ["Hat", "Candle", "Skull", "Hat", "Candle", "Skull"],
            "success_count": 7,
            "item_delay": 3,
            "item_timeout": 12,
            "item_spawn_delay": 1
        },
        {
            "item_pool": ["Hat", "Broom", "Skull", "Hand"],
            "success_count": 3,
            "item_delay": 3,
            "item_timeout": 15,
            "item_spawn_delay": 0.25
        },
        {
            "item_pool": ["Hat", "Skull", "Hand"],
            "success_count": 1,
            "item_delay": 3,
            "item_timeout": 10,
            "item_spawn_delay": 0.25
        },
        {
            "item_pool": ["Hat", "Skull", "Hand", "Hat", "Skull", "Hand"],
            "success_count": 8,
            "item_delay": 3,
            "item_timeout": 10,
            "item_spawn_delay": 1
        },
        {
            "item_pool": ["Pumpkin", "Cat", "Rat"],
            "success_count": 1,
            "item_delay": 7,
            "item_timeout": 10,
            "item_spawn_delay": 0.25
        },
        {
            "item_pool": ["Pumpkin", "Cat", "Rat"],
            "success_count": 3,
            "item_delay": 5,
            "item_timeout": 12,
            "item_spawn_delay": 0
        },
        {
            "item_pool": ["Pumpkin", "Cat", "Rat", "Pumpkin", "Cat", "Rat"],
            "success_count": 9,
            "item_delay": 3,
            "item_timeout": 9,
            "item_spawn_delay": 0
        },
        {
            "item_pool": ["Hat", "Broom", "Candle", "Cat", "Crow", "Hand", "Rat", "Scarecrow", "Skull"],
            "success_count": 8,
            "item_delay": 3,
        "item_timeout": 15,
            "item_spawn_delay": 0.25
        },
        {
            "on_start": "automation",
            "item_pool": ["Pumpkin"],
            "success_count": 1,
            "item_delay": 0,
            "item_timeout": 20,
            "item_spawn_delay": 0,
            "music": "SOUNDS_WAREHOUSE1"
        }
    ],
    "music": "SOUNDS_WAREHOUSE1",
    "tutorialOnStart": "intro",
    "tutorial": {
        
        "intro": {
            "dialog": [
                {
                    "message": "You will have a lot of orders coming through today"
                },
                {
                    "message": "You will need to muster everything you have to keep up"
                }
            ]
        },

        "automation": {
            "dialog": [
                {
                    "message": "You have been a stellar employee"
                },
                {
                    "message": "We have really been able to count on you to deliver"
                },
                {
                    "message": "We have some great news"
                },
                {
                    "message": "For us",
                    "effects": ["instant", "scale"],
                    "pre_delay": 1,
                    "tony_face": "annoyed"
                },
                {
                    "message": "We are replacing you with an automation spell"
                },
                {
                    "message": "As good as your work has been magic will do it better"
                },
                {
                    "message": "But we will let fulfull one more order for old times sake"
                },
                {
                    "message": "Be sure to pickup your paycheck before you leave"
                }
            ]
        }
    }
}